devpod/__init__.py
devpod/buildconfig.template
devpod/console.py
devpod-0.3.0.dist-info/entry_points.txt
devpod-0.3.0.dist-info/LICENSE
devpod-0.3.0.dist-info/WHEEL
devpod-0.3.0.dist-info/METADATA
devpod-0.3.0.dist-info/RECORD
