Metadata-Version: 2.1
Name: devpod
Version: 0.3.0
Summary: 
Home-page: https://github.com/davidstrauss/devpod
License: MIT
Author: David Strauss
Author-email: david@davidstrauss.net
Requires-Python: >=3.9,<4.0
Classifier: License :: OSI Approved :: MIT License
Classifier: Programming Language :: Python :: 3
Requires-Dist: click (>=7.1.2,<8.0.0)
Project-URL: Repository, https://github.com/davidstrauss/devpod
